PyHarshit/__init__.py
PyHarshit/db/__init__.py
PyHarshit/db/save.py
PyHarshit/db/tests.py
PyHarshit/tg/Control.py
PyHarshit/tg/FasterTg.py
PyHarshit/tg/Functions.py
PyHarshit/tg/__init__.py
PyHarshit/tg/extractor.py
PyHarshit/tg/tools.py
PyHarshit/tg/uploader.py
PyHarshit/tg/utils.py
PyHarshit/tools/__init__.py
PyHarshit/tools/anim.py
PyHarshit/tools/boolset.py
PyHarshit/tools/charset.py
PyHarshit/tools/fiverr.py
PyHarshit/tools/maths.py
PyHarshit/tools/utils.py
PyHarshit-0.0.8.dist-info/METADATA
PyHarshit-0.0.8.dist-info/WHEEL
PyHarshit-0.0.8.dist-info/top_level.txt
PyHarshit-0.0.8.dist-info/RECORD
