Metadata-Version: 2.1
Name: PyHarshit
Version: 0.0.8
Summary: Utlity file for my codes
Author: Harshit Shrivastav
Author-email: itsharshit@yandex.com
Requires-Python: >=3.8
Requires-Dist: pytz
Requires-Dist: python-decouple
Requires-Dist: telethon
Requires-Dist: aiofiles
Requires-Dist: aiohttp
Requires-Dist: opencv-python-headless
Requires-Dist: yt-dlp
Requires-Dist: requests
Requires-Dist: pyrogram
Requires-Dist: selenium (==4.9.0)
Requires-Dist: pytest (==7.0.1)
Requires-Dist: black (==23.1.0)
Requires-Dist: isort (==5.10.1)
Requires-Dist: pyclean (==2.0.0)
Requires-Dist: pre-commit (==3.3.2)
Requires-Dist: pylint (==2.12.2)
